tap_linear/__init__.py
tap_linear/client.py
tap_linear/queries/issues.py
tap_linear/schemas/issues.py
tap_linear/streams.py
tap_linear/tap.py
tap_linear/tests/__init__.py
tap_linear/tests/test_core.py
tap_linear-0.1.1.dist-info/entry_points.txt
tap_linear-0.1.1.dist-info/WHEEL
tap_linear-0.1.1.dist-info/METADATA
tap_linear-0.1.1.dist-info/RECORD
